anyrfc/__init__.py
anyrfc/_vendor/arpeggio/__init__.py
anyrfc/_vendor/arpeggio/cleanpeg.py
anyrfc/_vendor/arpeggio/export.py
anyrfc/_vendor/arpeggio/peg.py
anyrfc/_vendor/arpeggio/utils.py
anyrfc/auth/__init__.py
anyrfc/auth/oauth2/__init__.py
anyrfc/auth/sasl/__init__.py
anyrfc/core/__init__.py
anyrfc/core/anyio_compat.py
anyrfc/core/rfc_compliance.py
anyrfc/core/state_machine.py
anyrfc/core/streams.py
anyrfc/core/tls.py
anyrfc/core/types.py
anyrfc/core/uri.py
anyrfc/discovery/__init__.py
anyrfc/dns/__init__.py
anyrfc/email/__init__.py
anyrfc/email/imap/__init__.py
anyrfc/email/imap/client.py
anyrfc/email/imap/commands.py
anyrfc/email/imap/compliance.py
anyrfc/email/imap/extensions.py
anyrfc/email/imap/mailbox.py
anyrfc/email/imap/messages.py
anyrfc/email/imap/responses.py
anyrfc/email/smtp/__init__.py
anyrfc/email/smtp/client.py
anyrfc/file_transfer/__init__.py
anyrfc/file_transfer/ftp/__init__.py
anyrfc/file_transfer/ftps/__init__.py
anyrfc/file_transfer/sftp/__init__.py
anyrfc/iot/__init__.py
anyrfc/parsing/__init__.py
anyrfc/parsing/base.py
anyrfc/parsing/imap.py
anyrfc/parsing/imap_grammar.py
anyrfc/realtime/__init__.py
anyrfc/ssh/__init__.py
anyrfc/websocket/__init__.py
anyrfc/websocket/client.py
anyrfc/websocket/frames.py
anyrfc/websocket/handshake.py
anyrfc/websocket/state_machine.py
anyrfc-0.3.1.dist-info/METADATA
anyrfc-0.3.1.dist-info/WHEEL
anyrfc-0.3.1.dist-info/licenses/LICENSE
anyrfc-0.3.1.dist-info/RECORD
