Metadata-Version: 2.4
Name: anyrfc
Version: 0.3.1
Summary: Complete, RFC-compliant protocol clients using AnyIO structured concurrency
Project-URL: Homepage, https://github.com/elgertam/anyrfc
Project-URL: Documentation, https://github.com/elgertam/anyrfc#readme
Project-URL: Repository, https://github.com/elgertam/anyrfc.git
Project-URL: Bug Tracker, https://github.com/elgertam/anyrfc/issues
Project-URL: Changelog, https://github.com/elgertam/anyrfc/blob/master/CHANGELOG.md
Author-email: "Andrew M. Elgert" <andrew@elgert.org>
Maintainer-email: "Andrew M. Elgert" <andrew@elgert.org>
License-Expression: MIT
License-File: LICENSE
Keywords: anyio,async,client,imap,protocol,rfc,rfc5321,rfc6455,rfc9051,smtp,structured-concurrency,websocket
Classifier: Development Status :: 4 - Beta
Classifier: Framework :: AnyIO
Classifier: Intended Audience :: Developers
Classifier: License :: OSI Approved :: MIT License
Classifier: Operating System :: OS Independent
Classifier: Programming Language :: Python :: 3
Classifier: Programming Language :: Python :: 3.9
Classifier: Programming Language :: Python :: 3.10
Classifier: Programming Language :: Python :: 3.11
Classifier: Programming Language :: Python :: 3.12
Classifier: Programming Language :: Python :: 3.13
Classifier: Programming Language :: Python :: Implementation :: CPython
Classifier: Programming Language :: Python :: Implementation :: PyPy
Classifier: Topic :: Communications
Classifier: Topic :: Communications :: Email
Classifier: Topic :: Internet
Classifier: Topic :: Internet :: WWW/HTTP
Classifier: Topic :: Security
Classifier: Topic :: Security :: Cryptography
Classifier: Topic :: Software Development :: Libraries :: Python Modules
Classifier: Topic :: System :: Networking
Classifier: Typing :: Typed
Requires-Python: >=3.9
Requires-Dist: anyio>=4.5.1
Requires-Dist: exceptiongroup>=1.0.0; python_version < '3.11'
Requires-Dist: httpx>=0.25.0
Requires-Dist: typing-extensions>=4.0.0
